ptdos/__init__.py
ptdos/config.json
ptdos/ptdos.py
ptdos/version.py
ptdos/infrastructure/__init__.py
ptdos/infrastructure/attack.py
ptdos/infrastructure/factory.py
ptdos/infrastructure/loader.py
ptdos/misc/__init__.py
ptdos/misc/globalfuncs.py
ptdos/misc/ntp_servers.json
ptdos/misc/pt_http.py
ptdos/misc/pt_icmp.py
ptdos/misc/pt_ip.py
ptdos/misc/pt_ntp.py
ptdos/misc/pt_socket.py
ptdos/misc/pt_udp.py
ptdos/misc/user_agents.json
ptdos/monitoring/__init__.py
ptdos/monitoring/ptcheckservice.py
ptdos/plugins/__init__.py
ptdos/plugins/httpgetflood.py
ptdos/plugins/httpheadflood.py
ptdos/plugins/httppostflood.py
ptdos/plugins/icmpflood.py
ptdos/plugins/ntpampl.py
ptdos/plugins/pingofdeath.py
ptdos/plugins/plugin_template.py
ptdos/plugins/rudy.py
ptdos/plugins/slowloris.py
ptdos/plugins/smurf.py
ptdos/plugins/synflood.py
ptdos/plugins/udpflood.py
ptdos-0.1.1.dist-info/LICENSE
ptdos-0.1.1.dist-info/METADATA
ptdos-0.1.1.dist-info/WHEEL
ptdos-0.1.1.dist-info/entry_points.txt
ptdos-0.1.1.dist-info/top_level.txt
ptdos-0.1.1.dist-info/RECORD
